finna_crawler.py
finna_crawler-0.1.0.dist-info/METADATA
finna_crawler-0.1.0.dist-info/WHEEL
finna_crawler-0.1.0.dist-info/entry_points.txt
finna_crawler-0.1.0.dist-info/RECORD
