Metadata-Version: 2.1
Name: finna-crawler
Version: 0.1.0
Summary: Crawler to download data from the Finna OAI-PMH API
Author: Eetu Mäkelä
Author-email: eetu.makela@helsinki.fi
Requires-Python: >=3.10,<4.0
Classifier: Programming Language :: Python :: 3
Classifier: Programming Language :: Python :: 3.10
Classifier: Programming Language :: Python :: 3.11
Requires-Dist: Sickle (>=0.7.0,<0.8.0)
Requires-Dist: click (>=8.1.3,<9.0.0)
Requires-Dist: hereutil (>=0.1.1,<0.2.0)
Requires-Dist: tqdm (>=4.64.1,<5.0.0)
Requires-Dist: xopen[zstd] (>=1.7.0,<2.0.0)
